asyncarve/__init__.py
asyncarve/src/__init__.py
asyncarve/src/arve.py
asyncarve/src/const.py
asyncarve/src/exceptions.py
asyncarve/src/models.py
asyncarve-0.1.1.dist-info/METADATA
asyncarve-0.1.1.dist-info/WHEEL
asyncarve-0.1.1.dist-info/top_level.txt
asyncarve-0.1.1.dist-info/RECORD
